downdroid/__init__.py
downdroid/constants.py
downdroid/downdroid.py
downdroid/utils/__init__.py
downdroid/utils/argument_error.py
downdroid/utils/argv_error.py
downdroid/utils/documentation.py
downdroid/utils/download_file.py
downdroid/utils/get_releases.py
downdroid/utils/get_version_url.py
downdroid/utils/get_versions.py
downdroid-0.0.6.data/scripts/downdroid
downdroid-0.0.6.dist-info/LICENSE
downdroid-0.0.6.dist-info/METADATA
downdroid-0.0.6.dist-info/WHEEL
downdroid-0.0.6.dist-info/top_level.txt
downdroid-0.0.6.dist-info/RECORD
